{"updated_at": "2026-07-21T04:36:04Z", "windows": {"h1": [{"token": "0x0bd7d308f8e1639fab988df18a8011f41eacad73", "symbol": "WETH", "ageH": 143.4, "inWhales": 21, "inUsd": 739773.31, "outWhales": 3, "outUsd": 175721.4, "events": 4970}, {"token": "0x39dbed3a2bd333467115de45665cc57f813c4571", "symbol": "PONS", "ageH": 143.4, "inWhales": 18, "inUsd": 50691.13, "outWhales": 12, "outUsd": 423140.68, "events": 149}, {"token": "0x020bfc650a365f8bb26819deaabf3e21291018b4", "symbol": "CASHCAT", "ageH": 143.4, "inWhales": 12, "inUsd": 54333.87, "outWhales": 3, "outUsd": 21424.14, "events": 52}, {"token": "0x0339f5459fc690ac85f1782e15782a151b4a9e1b", "symbol": "WALLET", "ageH": 143.3, "inWhales": 2, "inUsd": 590.64, "outWhales": 1, "outUsd": 20724.07, "events": 12}, {"token": "0xe934e36a439c94017b64a3fece66af12099abf50", "symbol": "STONKBROKER", "ageH": 55.8, "inWhales": 5, "inUsd": 713.31, "outWhales": 3, "outUsd": 16754.17, "events": 18}, {"token": "0x8ecea3d0e648db646d824aa51eedeb16ac3d6878", "symbol": "WIRE", "ageH": 55.3, "inWhales": 8, "inUsd": 15189.74, "outWhales": 0, "outUsd": 0.0, "events": 28}, {"token": "0x45242320dbb855eea8fd36804c6487e10e97fcf9", "symbol": "TENDIES", "ageH": 142.2, "inWhales": 8, "inUsd": 11749.72, "outWhales": 1, "outUsd": 1460.43, "events": 25}, {"token": "0xb9fe2adf7c25ebe4081a2e228b02be05ebdf7410", "symbol": "HOODIO", "ageH": 141.7, "inWhales": 3, "inUsd": 4486.62, "outWhales": 1, "outUsd": 8163.96, "events": 10}, {"token": "0x56910d4409f3a0c78c64dd8d0545ff0705389870", "symbol": "Index", "ageH": 143.3, "inWhales": 6, "inUsd": 3358.18, "outWhales": 6, "outUsd": 9085.66, "events": 44}, {"token": "0x62c71cd34a52c30d894419cbcc55db2afa8032ea", "symbol": "YOLO", "ageH": 55.9, "inWhales": 4, "inUsd": 2082.03, "outWhales": 4, "outUsd": 6599.92, "events": 16}, {"token": "0x237c79c93c3eb8c61a2a2a7465a851b0381b8ba3", "symbol": "REAL", "ageH": 18.3, "inWhales": 6, "inUsd": 1197.37, "outWhales": 4, "outUsd": 6211.33, "events": 69}, {"token": "0xc6911796042b15d7fa4f6cde69e245ddcd3d9c31", "symbol": "VIRTUAL", "ageH": 141.7, "inWhales": 4, "inUsd": 7362.57, "outWhales": 0, "outUsd": 0.0, "events": 32}, {"token": "0x45f82ac5d507e988f7406935da8eefe495a360e0", "symbol": "BRODIE", "ageH": 143.4, "inWhales": 3, "inUsd": 3490.64, "outWhales": 3, "outUsd": 3525.0, "events": 7}, {"token": "0x7fe995a80075df3dc8ae11a9b82c7fe4202cd87f", "symbol": "HMM", "ageH": 44.5, "inWhales": 5, "inUsd": 1589.73, "outWhales": 2, "outUsd": 3911.5, "events": 20}, {"token": "0x791229e3ebd6cfdc3d8157f48722684173c29ad9", "symbol": "SLVR", "ageH": 142.8, "inWhales": 4, "inUsd": 4020.44, "outWhales": 1, "outUsd": 1320.76, "events": 6}, {"token": "0xd7321801caae694090694ff55a9323139f043b88", "symbol": "JUGGERNAUT", "ageH": 143.3, "inWhales": 4, "inUsd": 3466.74, "outWhales": 1, "outUsd": 1743.6, "events": 16}, {"token": "0x2443cde7097b4f7ec13596a56f41e8020de9455d", "symbol": "JACOBIAN", "ageH": 18.2, "inWhales": 5, "inUsd": 2536.43, "outWhales": 5, "outUsd": 2248.03, "events": 15}, {"token": "0x4a380618777eed8d513bcd6e983df3c5d2ba7777", "symbol": "RWA", "ageH": 141.9, "inWhales": 4, "inUsd": 2345.7, "outWhales": 1, "outUsd": 909.07, "events": 8}, {"token": "0xf8bc08092c06db6148114dcf82af881f1085f92b", "symbol": "WOOD", "ageH": 135.6, "inWhales": 0, "inUsd": 0.0, "outWhales": 1, "outUsd": 3194.37, "events": 1}, {"token": "0x2e8c31162b855a2ffa90f6f8634643ad6f111e18", "symbol": "AI", "ageH": 143.3, "inWhales": 3, "inUsd": 2837.26, "outWhales": 0, "outUsd": 0.0, "events": 4}, {"token": "0xf0568863195770965a6d8abb0aa87f4314b80320", "symbol": "SLIPPY", "ageH": 109.8, "inWhales": 3, "inUsd": 1.9, "outWhales": 2, "outUsd": 2501.42, "events": 7}, {"token": "0x7aa642e72289be3cafbac8dc529f10fa53bc7777", "symbol": "KOEKI", "ageH": 54.2, "inWhales": 3, "inUsd": 497.73, "outWhales": 7, "outUsd": 1849.32, "events": 11}, {"token": "0xe6864e4630d4d7a0cad2e61f6bc2c0dcad777712", "symbol": "LINK", "ageH": 142.2, "inWhales": 5, "inUsd": 1791.23, "outWhales": 1, "outUsd": 408.32, "events": 6}, {"token": "0x4f0ee38e4632901b81c240e9b362701f682ba55e", "symbol": "SHREK", "ageH": 50.8, "inWhales": 6, "inUsd": 1569.37, "outWhales": 1, "outUsd": 628.44, "events": 13}, {"token": "0x0af77e27f535256965944e617a386570f5c0432a", "symbol": "STEEL", "ageH": 55.9, "inWhales": 2, "inUsd": 0.04, "outWhales": 1, "outUsd": 2160.01, "events": 3}, {"token": "0x75c8258eaa6d0f94b82951194191ca3efb0bcbe2", "symbol": "MEOW", "ageH": 143.3, "inWhales": 3, "inUsd": 146.82, "outWhales": 2, "outUsd": 1856.08, "events": 7}, {"token": "0x3450598e419abb5609f60e4b2fda127ff0897777", "symbol": "FLETCH", "ageH": 142.8, "inWhales": 4, "inUsd": 601.99, "outWhales": 2, "outUsd": 1346.54, "events": 8}, {"token": "0xf4c450c1570c2dbda91de1ed2e39995a15028c97", "symbol": "HODL", "ageH": 134.3, "inWhales": 2, "inUsd": 755.1, "outWhales": 1, "outUsd": 1158.25, "events": 4}, {"token": "0xaf4c10fef50059d1e3e8ab1c80e46db6a76098b4", "symbol": "BOWYER", "ageH": 82.9, "inWhales": 3, "inUsd": 688.11, "outWhales": 2, "outUsd": 1033.24, "events": 9}, {"token": "0xc23d7218512c672ba6e87b7f8bcce53355f55931", "symbol": "BOWLINE", "ageH": 111.2, "inWhales": 0, "inUsd": 0.0, "outWhales": 1, "outUsd": 1694.95, "events": 1}, {"token": "0x43eea882b845a8493152ebc55cf30ae9281b02d5", "symbol": "FIRE", "ageH": 50.7, "inWhales": 0, "inUsd": 0.0, "outWhales": 1, "outUsd": 1687.7, "events": 1}, {"token": "0xc35968c7f5475bb03a43c7382526f4118e01c0de", "symbol": "VISTA", "ageH": 110.0, "inWhales": 2, "inUsd": 836.18, "outWhales": 1, "outUsd": 835.94, "events": 4}, {"token": "0xdbcec8db3e21c1612a22b39d195d7d654cad00af", "symbol": "Jimothy", "ageH": 87.0, "inWhales": 1, "inUsd": 1665.58, "outWhales": 0, "outUsd": 0.0, "events": 6}, {"token": "0x8639b074da6a2903faed8da95c0a3cb936f6ad91", "symbol": "CHANGE", "ageH": 50.1, "inWhales": 0, "inUsd": 0.0, "outWhales": 2, "outUsd": 1465.2, "events": 2}, {"token": "0x17c0ea83edf05859bc9339529ae85fca71301d67", "symbol": "GLS", "ageH": 10.3, "inWhales": 2, "inUsd": 666.9, "outWhales": 1, "outUsd": 666.65, "events": 16}, {"token": "0xed88fd767eb5527a107ad0b4a36b82cbd50ff9d4", "symbol": "ZTOCKS", "ageH": 18.1, "inWhales": 1, "inUsd": 654.29, "outWhales": 1, "outUsd": 654.28, "events": 3}, {"token": "0x4d7b52e644d830d47510440477cb50295d9a8148", "symbol": "4FUN", "ageH": 85.5, "inWhales": 1, "inUsd": 0.08, "outWhales": 1, "outUsd": 1277.66, "events": 2}, {"token": "0x28e448946e042c2d4c38f6e80cd724e415ad95bb", "symbol": "CHAD", "ageH": 81.0, "inWhales": 2, "inUsd": 805.05, "outWhales": 1, "outUsd": 470.45, "events": 3}, {"token": "0x6365fd27ddefc42f50895994b67b04fab5f08d5e", "symbol": "$1", "ageH": 143.3, "inWhales": 2, "inUsd": 0.02, "outWhales": 1, "outUsd": 1265.78, "events": 3}, {"token": "0xfb1bcb6817f7b8fa86896d3253b16aeb7bd6a5a8", "symbol": "WORTH", "ageH": 143.3, "inWhales": 0, "inUsd": 0.0, "outWhales": 1, "outUsd": 1189.06, "events": 1}, {"token": "0x5f94e24a3293cf12c97d8b21c2f960adf471c951", "symbol": "UNICORN", "ageH": 139.0, "inWhales": 0, "inUsd": 0.0, "outWhales": 2, "outUsd": 1132.01, "events": 2}, {"token": "0xd80afe3be875a14155fdd96d39669a6734e12036", "symbol": "BUFFCAT", "ageH": 141.0, "inWhales": 1, "inUsd": 565.47, "outWhales": 1, "outUsd": 565.47, "events": 2}, {"token": "0x39e0d9057bd9039cd14590f54de20b9d3457c56e", "symbol": "NOXA", "ageH": 135.3, "inWhales": 4, "inUsd": 1087.9, "outWhales": 0, "outUsd": 0.0, "events": 4}, {"token": "0xdaffa3b70d100286f4fbe1ed6de7c227d94f5912", "symbol": "AGENTIQ", "ageH": 108.8, "inWhales": 1, "inUsd": 1073.62, "outWhales": 0, "outUsd": 0.0, "events": 2}, {"token": "0x40e836f547653691b74c0d68fff60befe36cb024", "symbol": "FAMILY", "ageH": 143.4, "inWhales": 2, "inUsd": 1038.74, "outWhales": 0, "outUsd": 0.0, "events": 2}, {"token": "0x5d86691d883f8962d38fd62136fb761ad3a629ea", "symbol": "MIM", "ageH": 143.4, "inWhales": 3, "inUsd": 218.96, "outWhales": 2, "outUsd": 750.23, "events": 8}, {"token": "0xa80eb66b3e0cf66ccb46f8b8c9e7ff5803eeb820", "symbol": "WEN", "ageH": 143.3, "inWhales": 2, "inUsd": 968.18, "outWhales": 0, "outUsd": 0.0, "events": 2}, {"token": "0x8f100e99ddf699320724e37cb866770381d47382", "symbol": "ROBINHOOD", "ageH": 143.3, "inWhales": 4, "inUsd": 633.24, "outWhales": 1, "outUsd": 277.21, "events": 5}, {"token": "0x4ef48d3e2d7527146379d76add014cff48011436", "symbol": "WISP", "ageH": 11.8, "inWhales": 1, "inUsd": 451.17, "outWhales": 1, "outUsd": 430.39, "events": 6}, {"token": "0x0e07565159b1e40caa71d4edf2547cc042014523", "symbol": "WOLVES", "ageH": 54.2, "inWhales": 2, "inUsd": 3.33, "outWhales": 1, "outUsd": 870.35, "events": 3}, {"token": "0xab26d5b48bd07f1248a66fd817036f785078b51d", "symbol": "KANSO", "ageH": 101.9, "inWhales": 3, "inUsd": 867.15, "outWhales": 0, "outUsd": 0.0, "events": 4}, {"token": "0x3c6a3a92b8163ecc7b6e3e8e6c2cb00b2c9c7777", "symbol": "530A", "ageH": 142.9, "inWhales": 1, "inUsd": 203.08, "outWhales": 2, "outUsd": 650.74, "events": 3}, {"token": "0xa361419ad69956d611244520bf3afa88ca783f3e", "symbol": "POND", "ageH": 49.3, "inWhales": 0, "inUsd": 0.0, "outWhales": 2, "outUsd": 837.42, "events": 2}, {"token": "0x6689ab375aaaa9aed78aaaba2e8edcc547478cf1", "symbol": "KALEIDO", "ageH": 117.8, "inWhales": 0, "inUsd": 0.0, "outWhales": 1, "outUsd": 820.04, "events": 1}, {"token": "0x27c5a4353a710af81a27c5386f0dc93a26efeea8", "symbol": "MARS", "ageH": 50.6, "inWhales": 1, "inUsd": 783.44, "outWhales": 0, "outUsd": 0.0, "events": 1}, {"token": "0x43454d90daf71bcf17d68174d6fe99abc352d592", "symbol": "TWILL", "ageH": 14.1, "inWhales": 1, "inUsd": 280.1, "outWhales": 1, "outUsd": 431.87, "events": 3}, {"token": "0x912136b5ce6063591e6ae47edc76cde98235860e", "symbol": "GREENBOW", "ageH": 143.3, "inWhales": 0, "inUsd": 0.0, "outWhales": 1, "outUsd": 702.7, "events": 1}, {"token": "0x164d9da79722c5294369e79807980e0bff257777", "symbol": "utopia", "ageH": 49.7, "inWhales": 2, "inUsd": 0.65, "outWhales": 1, "outUsd": 686.3, "events": 3}, {"token": "0x0b9fa1f756f7a374abd45642a2eea8aa78fbcba3", "symbol": "moo", "ageH": 33.4, "inWhales": 0, "inUsd": 0.0, "outWhales": 1, "outUsd": 671.37, "events": 1}, {"token": "0x43e7cb9984ad95aa808ac21998cc8d5f909e47af", "symbol": "VIM", "ageH": 136.4, "inWhales": 0, "inUsd": 0.0, "outWhales": 1, "outUsd": 659.5, "events": 1}, {"token": "0x859ead0ee2fd39a2804bb27713742577f7be79c1", "symbol": "CC", "ageH": 35.6, "inWhales": 0, "inUsd": 0.0, "outWhales": 1, "outUsd": 635.42, "events": 1}, {"token": "0x8d4dfaaa4198b6486e0293fec914c2b6a821d4dc", "symbol": "KITSU", "ageH": 143.4, "inWhales": 3, "inUsd": 624.46, "outWhales": 0, "outUsd": 0.0, "events": 5}, {"token": "0xb1cb27f78b7335df8c3d8ebf0881a15bed6beb60", "symbol": "SWOOD", "ageH": 142.4, "inWhales": 0, "inUsd": 0.0, "outWhales": 1, "outUsd": 616.08, "events": 1}, {"token": "0x7f3aecc694f298e0010f8a31ec49250506bb3b7c", "symbol": "YAM", "ageH": 52.2, "inWhales": 3, "inUsd": 600.25, "outWhales": 0, "outUsd": 0.0, "events": 4}, {"token": "0x9e94c8b5a0caeda5d0471c3a9f5ed4f3519d88c7", "symbol": "ROCKET", "ageH": 8.1, "inWhales": 3, "inUsd": 561.13, "outWhales": 0, "outUsd": 0.0, "events": 3}, {"token": "0xf2915d1e3c1b0c769d0c756ec43f1c1f6c99cd03", "symbol": "ARROW", "ageH": 142.8, "inWhales": 1, "inUsd": 8.87, "outWhales": 1, "outUsd": 520.98, "events": 7}, {"token": "0xb6d695d5fbcebd837f6b9f214c9beee8ba90762b", "symbol": "VANTIS", "ageH": 103.8, "inWhales": 0, "inUsd": 0.0, "outWhales": 1, "outUsd": 518.99, "events": 1}, {"token": "0x4f298b7b07abcb81e4c097c28dfe68d49f17c0de", "symbol": "HPEPE", "ageH": 53.7, "inWhales": 0, "inUsd": 0.0, "outWhales": 1, "outUsd": 517.08, "events": 1}, {"token": "0x8e62f281f282686fca6dcb39288069a93fc23f1c", "symbol": "HOODRAT", "ageH": 143.2, "inWhales": 2, "inUsd": 515.94, "outWhales": 0, "outUsd": 0.0, "events": 5}, {"token": "0x5ad6fad7794f4118fa119dc6f5652f360f3b8eb5", "symbol": "VLAD", "ageH": 137.4, "inWhales": 0, "inUsd": 0.0, "outWhales": 1, "outUsd": 453.36, "events": 1}, {"token": "0x675f1e6871872f1e732a0d8a5014a28333c887a0", "symbol": "RWAX", "ageH": 38.3, "inWhales": 0, "inUsd": 0.0, "outWhales": 1, "outUsd": 446.62, "events": 1}, {"token": "0xce547381944a80695a151a6420660527e874bb47", "symbol": "WOLF", "ageH": 27.6, "inWhales": 2, "inUsd": 441.83, "outWhales": 0, "outUsd": 0.0, "events": 2}, {"token": "0xa737df5de18e3aa6b0bf8c2e9846ed699f6f2aeb", "symbol": "PONSTAR", "ageH": 143.3, "inWhales": 2, "inUsd": 434.21, "outWhales": 0, "outUsd": 0.0, "events": 2}, {"token": "0x8ab3c1a9db67a2ce1b70c2bb381e28df3769654b", "symbol": "BUCK", "ageH": 132.0, "inWhales": 1, "inUsd": 0.12, "outWhales": 1, "outUsd": 431.05, "events": 4}, {"token": "0x11e6962ec578f394e366bd84ebf46a0643c6a43e", "symbol": "RWA", "ageH": 143.0, "inWhales": 1, "inUsd": 421.65, "outWhales": 0, "outUsd": 0.0, "events": 2}, {"token": "0xd125f8f710b052b66ae5ef2113957c83d25a7777", "symbol": "HOODED", "ageH": 29.3, "inWhales": 0, "inUsd": 0.0, "outWhales": 1, "outUsd": 419.67, "events": 1}, {"token": "0x2355431b83b1a8e40172d099d90243d8d666b56b", "symbol": "VIBECAT", "ageH": 143.3, "inWhales": 0, "inUsd": 0.0, "outWhales": 1, "outUsd": 401.36, "events": 1}, {"token": "0xf706fbacf8e59299effc44a96e57dd1322b3ec19", "symbol": "JOHN", "ageH": 137.8, "inWhales": 3, "inUsd": 396.18, "outWhales": 0, "outUsd": 0.0, "events": 5}, {"token": "0xd4052415613b34af236024b895574c467f65b6dd", "symbol": "4663", "ageH": 143.4, "inWhales": 1, "inUsd": 0.06, "outWhales": 1, "outUsd": 390.93, "events": 3}, {"token": "0xf4eaec43e22251547fbd2cb2f153e041c3aa4ea6", "symbol": "TEST", "ageH": 142.6, "inWhales": 2, "inUsd": 348.74, "outWhales": 0, "outUsd": 0.0, "events": 3}, {"token": "0x1a9874647b22cde3b97dd5e8bdca67f30e8ec0de", "symbol": "STACHE", "ageH": 43.5, "inWhales": 0, "inUsd": 0.0, "outWhales": 1, "outUsd": 313.02, "events": 1}, {"token": "0xca70d457418b90493e5735de6ec4410c3945498e", "symbol": "WATCH", "ageH": 10.2, "inWhales": 2, "inUsd": 153.14, "outWhales": 1, "outUsd": 153.14, "events": 3}, {"token": "0x2d07db58fae9b53c795f667b4579508cbe0a3fcc", "symbol": "?", "ageH": 137.5, "inWhales": 2, "inUsd": 286.05, "outWhales": 0, "outUsd": 0.0, "events": 2}, {"token": "0x01637b14b7378b99de75a64d50656d98488d9a4d", "symbol": "MARIAN", "ageH": 143.4, "inWhales": 4, "inUsd": 278.48, "outWhales": 0, "outUsd": 0.0, "events": 5}, {"token": "0x8bd7658dd2889d93c31055f5ce7135c9a24be7df", "symbol": "CRAMER", "ageH": 96.3, "inWhales": 2, "inUsd": 274.68, "outWhales": 0, "outUsd": 0.0, "events": 2}, {"token": "0xf419e6f419b3801c9e8b553aa34f883507d4fa8e", "symbol": "STARTUP", "ageH": 135.3, "inWhales": 0, "inUsd": 0.0, "outWhales": 1, "outUsd": 268.22, "events": 1}, {"token": "0xc0d6457c16cc70d6790dd43521c899c87ce02f35", "symbol": "META", "ageH": 129.8, "inWhales": 0, "inUsd": 0.0, "outWhales": 1, "outUsd": 231.16, "events": 1}, {"token": "0x7f0404070cf6fb703af9f3b89f84af3ffe2a54b3", "symbol": "FILL", "ageH": 12.4, "inWhales": 1, "inUsd": 208.14, "outWhales": 0, "outUsd": 0.0, "events": 1}, {"token": "0xb0b8f5078f1c795714664569744670bdf856387b", "symbol": "POONS", "ageH": 51.2, "inWhales": 0, "inUsd": 0.0, "outWhales": 1, "outUsd": 207.74, "events": 1}, {"token": "0xb4bbd64031400d7ef2b96d262be51423cf7342ed", "symbol": "BUY", "ageH": 13.1, "inWhales": 3, "inUsd": 199.29, "outWhales": 0, "outUsd": 0.0, "events": 3}, {"token": "0xf05babb8172bea20e974b458c593399be11250dd", "symbol": "GRACE", "ageH": 143.3, "inWhales": 1, "inUsd": 192.46, "outWhales": 0, "outUsd": 0.0, "events": 1}, {"token": "0x2e0847e8910a9732eb3fb1bb4b70a580adad4fe3", "symbol": "GOOGL", "ageH": 143.2, "inWhales": 0, "inUsd": 0.0, "outWhales": 3, "outUsd": 190.44, "events": 3}, {"token": "0x7b147b486ac3ccc2192ef9ce1de94d987174a352", "symbol": "NVRNAP", "ageH": 56.1, "inWhales": 1, "inUsd": 190.3, "outWhales": 0, "outUsd": 0.0, "events": 1}, {"token": "0x12f190a9f9d7d37a250758b26824b97ce941bf54", "symbol": "AMZN", "ageH": 142.1, "inWhales": 0, "inUsd": 0.0, "outWhales": 3, "outUsd": 188.26, "events": 3}, {"token": "0x0de3379809dcf87c2c8b51c6d54c96f98f541440", "symbol": "WAGMI", "ageH": 50.6, "inWhales": 3, "inUsd": 187.84, "outWhales": 0, "outUsd": 0.0, "events": 3}, {"token": "0x8072cf881809d1ce5157589a64cd11452cc5a0e2", "symbol": "ACATS", "ageH": 140.6, "inWhales": 1, "inUsd": 186.85, "outWhales": 0, "outUsd": 0.0, "events": 1}, {"token": "0xe20cf2f31056539fcfa72f45c5eb63bdbb3806d8", "symbol": "SWARM", "ageH": 12.3, "inWhales": 1, "inUsd": 185.34, "outWhales": 0, "outUsd": 0.0, "events": 1}, {"token": "0x0a713a88e05787d455954dabdba3b69a92518505", "symbol": "BARBELL", "ageH": 142.8, "inWhales": 0, "inUsd": 0.0, "outWhales": 1, "outUsd": 182.57, "events": 1}, {"token": "0x186c9122868401c05d56fa5984867417ece07777", "symbol": "Stockcoin", "ageH": 55.5, "inWhales": 1, "inUsd": 181.57, "outWhales": 0, "outUsd": 0.0, "events": 1}, {"token": "0x311d99333aae6f4b19d3829ba84ded8df0c1e0de", "symbol": "HODL", "ageH": 51.0, "inWhales": 0, "inUsd": 0.0, "outWhales": 1, "outUsd": 172.28, "events": 1}, {"token": "0x38bea5c0f7e4ac83280a602801ce17044d717777", "symbol": "RobinBall", "ageH": 142.9, "inWhales": 0, "inUsd": 0.0, "outWhales": 1, "outUsd": 170.01, "events": 1}, {"token": "0x91e2ce85c223cd55b0cf76ca668a0e61ed696c6b", "symbol": "VLAD", "ageH": 97.1, "inWhales": 1, "inUsd": 166.96, "outWhales": 0, "outUsd": 0.0, "events": 1}, {"token": "0x4a0e65a3eccec6dbe60ae065f2e7bb85fae35eea", "symbol": "SPCX", "ageH": 143.2, "inWhales": 0, "inUsd": 0.0, "outWhales": 3, "outUsd": 156.1, "events": 3}, {"token": "0xd3165c9d0993330c1132c59fc6513b08639211c5", "symbol": "FRIDAY", "ageH": 53.2, "inWhales": 2, "inUsd": 155.4, "outWhales": 0, "outUsd": 0.0, "events": 2}, {"token": "0x5354da49d1236f3e8ffc248bdb3510fa49c1dafc", "symbol": "GROYPER", "ageH": 132.1, "inWhales": 0, "inUsd": 0.0, "outWhales": 1, "outUsd": 154.75, "events": 1}, {"token": "0xe4e08a1d973546e399a730c903e750e4c17aec15", "symbol": "PEPE", "ageH": 133.0, "inWhales": 0, "inUsd": 0.0, "outWhales": 1, "outUsd": 146.51, "events": 1}, {"token": "0x86a24426d1fc5dfdee454120af3ecc3cc552789b", "symbol": "pow", "ageH": 91.1, "inWhales": 1, "inUsd": 0.09, "outWhales": 1, "outUsd": 142.41, "events": 2}, {"token": "0x8ff92566f2e81bdd68edfaa8cde73942a723796b", "symbol": "VEX", "ageH": 143.4, "inWhales": 6, "inUsd": 134.53, "outWhales": 0, "outUsd": 0.0, "events": 13}, {"token": "0x5e360298fd7310f8cf29962fb90ed59e88a85f5d", "symbol": "FUGAZI", "ageH": 122.2, "inWhales": 0, "inUsd": 0.0, "outWhales": 1, "outUsd": 121.92, "events": 1}, {"token": "0x863ff2b3dd1d7ab2637131b8593926e9e9e170cc", "symbol": "SNOP", "ageH": 135.7, "inWhales": 1, "inUsd": 109.35, "outWhales": 0, "outUsd": 0.0, "events": 1}, {"token": "0x35853bc429ea67bc85ba2cbb4b0ae71778ecaecb", "symbol": "EARLY", "ageH": 49.9, "inWhales": 0, "inUsd": 0.0, "outWhales": 1, "outUsd": 89.23, "events": 1}, {"token": "0x4f732d5b29d7fc20d77ce23cb6f511a0f0400acc", "symbol": "DICKBUTT", "ageH": 18.1, "inWhales": 0, "inUsd": 0.0, "outWhales": 1, "outUsd": 89.06, "events": 1}, {"token": "0xcec4cfd9064dd88fc87de3db28848ff099516969", "symbol": "MCAT", "ageH": 27.9, "inWhales": 1, "inUsd": 85.19, "outWhales": 0, "outUsd": 0.0, "events": 1}, {"token": "0x97d811b8814ef5150595673ebd1c0075bf8a638b", "symbol": "VROG", "ageH": 0.6, "inWhales": 0, "inUsd": 0.0, "outWhales": 1, "outUsd": 76.97, "events": 1}, {"token": "0xc4d8ee1b0db4499c89154ddc35376338b8e4ec61", "symbol": "APE", "ageH": 116.8, "inWhales": 1, "inUsd": 70.93, "outWhales": 0, "outUsd": 0.0, "events": 1}, {"token": "0xa80f6f4f07a49f1b34cbd1e7b3ec689d8fb986bd", "symbol": "WOLVES", "ageH": 50.9, "inWhales": 1, "inUsd": 68.62, "outWhales": 0, "outUsd": 0.0, "events": 1}, {"token": "0xe93237c50d904957cf27e7b1133b510c669c2e74", "symbol": "MSFT", "ageH": 142.1, "inWhales": 0, "inUsd": 0.0, "outWhales": 2, "outUsd": 67.38, "events": 2}, {"token": "0x3ba2f579d63d138739ce5784cf1f8164f2f69ac7", "symbol": "GMEBAY", "ageH": 87.1, "inWhales": 0, "inUsd": 0.0, "outWhales": 1, "outUsd": 65.48, "events": 1}, {"token": "0x82c6fe1082dcc6e71e9411cef2846a0a107c34ab", "symbol": "MSFT", "ageH": 17.8, "inWhales": 1, "inUsd": 30.76, "outWhales": 1, "outUsd": 30.77, "events": 3}, {"token": "0x02cf701ddb38ec16c3b13eb410dff284c78d7cbb", "symbol": "Cheems", "ageH": 0.2, "inWhales": 0, "inUsd": 0.0, "outWhales": 1, "outUsd": 60.85, "events": 1}], "h6": [{"token": "0x0bd7d308f8e1639fab988df18a8011f41eacad73", "symbol": "WETH", "ageH": 143.4, "inWhales": 24, "inUsd": 3812559.54, "outWhales": 4, "outUsd": 259276.59, "events": 19685}, {"token": "0x39dbed3a2bd333467115de45665cc57f813c4571", "symbol": "PONS", "ageH": 143.4, "inWhales": 90, "inUsd": 881793.65, "outWhales": 72, "outUsd": 1025124.87, "events": 1474}, {"token": "0x020bfc650a365f8bb26819deaabf3e21291018b4", "symbol": "CASHCAT", "ageH": 143.4, "inWhales": 30, "inUsd": 404553.43, "outWhales": 31, "outUsd": 299730.79, "events": 358}, {"token": "0x56910d4409f3a0c78c64dd8d0545ff0705389870", "symbol": "Index", "ageH": 143.3, "inWhales": 40, "inUsd": 264630.14, "outWhales": 30, "outUsd": 270109.88, "events": 301}, {"token": "0xe934e36a439c94017b64a3fece66af12099abf50", "symbol": "STONKBROKER", "ageH": 55.8, "inWhales": 14, "inUsd": 109949.64, "outWhales": 12, "outUsd": 90258.86, "events": 164}, {"token": "0x62c71cd34a52c30d894419cbcc55db2afa8032ea", "symbol": "YOLO", "ageH": 55.9, "inWhales": 28, "inUsd": 115413.73, "outWhales": 22, "outUsd": 60461.59, "events": 281}, {"token": "0x45242320dbb855eea8fd36804c6487e10e97fcf9", "symbol": "TENDIES", "ageH": 142.2, "inWhales": 19, "inUsd": 68539.65, "outWhales": 15, "outUsd": 100682.39, "events": 177}, {"token": "0xc6911796042b15d7fa4f6cde69e245ddcd3d9c31", "symbol": "VIRTUAL", "ageH": 141.7, "inWhales": 7, "inUsd": 13392.28, "outWhales": 4, "outUsd": 122822.23, "events": 82}, {"token": "0x237c79c93c3eb8c61a2a2a7465a851b0381b8ba3", "symbol": "REAL", "ageH": 18.3, "inWhales": 21, "inUsd": 47652.91, "outWhales": 18, "outUsd": 63422.94, "events": 249}, {"token": "0x0339f5459fc690ac85f1782e15782a151b4a9e1b", "symbol": "WALLET", "ageH": 143.3, "inWhales": 9, "inUsd": 22569.96, "outWhales": 4, "outUsd": 35509.97, "events": 62}, {"token": "0x45f82ac5d507e988f7406935da8eefe495a360e0", "symbol": "BRODIE", "ageH": 143.4, "inWhales": 32, "inUsd": 23144.25, "outWhales": 18, "outUsd": 17403.47, "events": 132}, {"token": "0x7fe995a80075df3dc8ae11a9b82c7fe4202cd87f", "symbol": "HMM", "ageH": 44.5, "inWhales": 13, "inUsd": 15531.49, "outWhales": 8, "outUsd": 24102.15, "events": 131}, {"token": "0x8ecea3d0e648db646d824aa51eedeb16ac3d6878", "symbol": "WIRE", "ageH": 55.3, "inWhales": 15, "inUsd": 26326.93, "outWhales": 7, "outUsd": 11543.93, "events": 111}, {"token": "0x8ff92566f2e81bdd68edfaa8cde73942a723796b", "symbol": "VEX", "ageH": 143.4, "inWhales": 12, "inUsd": 25043.34, "outWhales": 2, "outUsd": 8508.3, "events": 78}, {"token": "0x8f100e99ddf699320724e37cb866770381d47382", "symbol": "ROBINHOOD", "ageH": 143.3, "inWhales": 17, "inUsd": 19303.3, "outWhales": 11, "outUsd": 13782.1, "events": 69}, {"token": "0x2e8c31162b855a2ffa90f6f8634643ad6f111e18", "symbol": "AI", "ageH": 143.3, "inWhales": 17, "inUsd": 27769.6, "outWhales": 5, "outUsd": 4106.95, "events": 36}, {"token": "0xd7321801caae694090694ff55a9323139f043b88", "symbol": "JUGGERNAUT", "ageH": 143.3, "inWhales": 10, "inUsd": 14382.03, "outWhales": 6, "outUsd": 15678.24, "events": 84}, {"token": "0xf0568863195770965a6d8abb0aa87f4314b80320", "symbol": "SLIPPY", "ageH": 109.8, "inWhales": 8, "inUsd": 13016.55, "outWhales": 9, "outUsd": 13495.73, "events": 62}, {"token": "0xf2915d1e3c1b0c769d0c756ec43f1c1f6c99cd03", "symbol": "ARROW", "ageH": 142.8, "inWhales": 9, "inUsd": 12285.6, "outWhales": 5, "outUsd": 11907.66, "events": 61}, {"token": "0xaf4c10fef50059d1e3e8ab1c80e46db6a76098b4", "symbol": "BOWYER", "ageH": 82.9, "inWhales": 11, "inUsd": 7991.38, "outWhales": 8, "outUsd": 8880.47, "events": 42}, {"token": "0x4a380618777eed8d513bcd6e983df3c5d2ba7777", "symbol": "RWA", "ageH": 141.9, "inWhales": 9, "inUsd": 8909.44, "outWhales": 5, "outUsd": 7290.39, "events": 35}, {"token": "0x1abf16f660ccbaa22ce8646deb1b63635d582228", "symbol": "FONZ", "ageH": 117.4, "inWhales": 11, "inUsd": 6501.81, "outWhales": 7, "outUsd": 8631.95, "events": 107}, {"token": "0x6f572e8020247324d7b9dc15c297a32e4187df1c", "symbol": "IN", "ageH": 15.4, "inWhales": 3, "inUsd": 31.28, "outWhales": 5, "outUsd": 13540.41, "events": 36}, {"token": "0xb9fe2adf7c25ebe4081a2e228b02be05ebdf7410", "symbol": "HOODIO", "ageH": 141.7, "inWhales": 4, "inUsd": 4487.17, "outWhales": 2, "outUsd": 8391.86, "events": 12}, {"token": "0xb165b9223687db26f26a31d2611d4cf3ebfa3d2e", "symbol": "DEMO2", "ageH": 13.3, "inWhales": 1, "inUsd": 6069.28, "outWhales": 1, "outUsd": 6069.28, "events": 2}, {"token": "0xb47f4702deb124cb4eb6286be83c9d84277c6239", "symbol": "KARMA", "ageH": 95.0, "inWhales": 6, "inUsd": 447.71, "outWhales": 2, "outUsd": 11213.07, "events": 30}, {"token": "0x2443cde7097b4f7ec13596a56f41e8020de9455d", "symbol": "JACOBIAN", "ageH": 18.2, "inWhales": 12, "inUsd": 6371.58, "outWhales": 9, "outUsd": 4785.9, "events": 48}, {"token": "0xa737df5de18e3aa6b0bf8c2e9846ed699f6f2aeb", "symbol": "PONSTAR", "ageH": 143.3, "inWhales": 10, "inUsd": 5884.96, "outWhales": 7, "outUsd": 4879.53, "events": 29}, {"token": "0x791229e3ebd6cfdc3d8157f48722684173c29ad9", "symbol": "SLVR", "ageH": 142.8, "inWhales": 7, "inUsd": 6652.76, "outWhales": 3, "outUsd": 3640.98, "events": 30}, {"token": "0x71d6a215344b61f36514214d9cbace82643f066d", "symbol": "CASHCAT", "ageH": 106.0, "inWhales": 16, "inUsd": 6525.09, "outWhales": 12, "outUsd": 3392.1, "events": 72}, {"token": "0x3450598e419abb5609f60e4b2fda127ff0897777", "symbol": "FLETCH", "ageH": 142.8, "inWhales": 6, "inUsd": 2947.21, "outWhales": 8, "outUsd": 6768.15, "events": 37}, {"token": "0x887df15e95423acdd181aed8c6144505e1ea6969", "symbol": "MOTION", "ageH": 30.0, "inWhales": 2, "inUsd": 8878.9, "outWhales": 2, "outUsd": 777.2, "events": 4}, {"token": "0xf4c450c1570c2dbda91de1ed2e39995a15028c97", "symbol": "HODL", "ageH": 134.3, "inWhales": 5, "inUsd": 4636.69, "outWhales": 2, "outUsd": 3846.1, "events": 18}, {"token": "0x75c8258eaa6d0f94b82951194191ca3efb0bcbe2", "symbol": "MEOW", "ageH": 143.3, "inWhales": 6, "inUsd": 3770.51, "outWhales": 4, "outUsd": 4275.05, "events": 31}, {"token": "0x164d9da79722c5294369e79807980e0bff257777", "symbol": "utopia", "ageH": 49.7, "inWhales": 7, "inUsd": 3261.9, "outWhales": 5, "outUsd": 4769.27, "events": 33}, {"token": "0xa80eb66b3e0cf66ccb46f8b8c9e7ff5803eeb820", "symbol": "WEN", "ageH": 143.3, "inWhales": 4, "inUsd": 5363.89, "outWhales": 1, "outUsd": 2029.51, "events": 8}, {"token": "0x385354ac9cc1bfc1776df4e65a33ee2278631d8d", "symbol": "GAPPY", "ageH": 117.0, "inWhales": 8, "inUsd": 4240.17, "outWhales": 2, "outUsd": 3068.74, "events": 22}, {"token": "0x77581054581b9c525e7dd7a0155de43867532d03", "symbol": "WISHBONE", "ageH": 143.3, "inWhales": 7, "inUsd": 4463.5, "outWhales": 2, "outUsd": 2331.84, "events": 34}, {"token": "0x53db64dfff64918ffd7c706c9b78a2d627cc0576", "symbol": "ARROWMAN", "ageH": 13.4, "inWhales": 7, "inUsd": 4649.96, "outWhales": 4, "outUsd": 1926.68, "events": 19}, {"token": "0x41af7e794dee45eefab49b6c387eac9368d69c4d", "symbol": "QUANT", "ageH": 56.1, "inWhales": 4, "inUsd": 2034.05, "outWhales": 6, "outUsd": 4451.41, "events": 16}, {"token": "0x40e836f547653691b74c0d68fff60befe36cb024", "symbol": "FAMILY", "ageH": 143.4, "inWhales": 6, "inUsd": 3675.43, "outWhales": 3, "outUsd": 2381.27, "events": 31}, {"token": "0x9e94c8b5a0caeda5d0471c3a9f5ed4f3519d88c7", "symbol": "ROCKET", "ageH": 8.1, "inWhales": 10, "inUsd": 5001.11, "outWhales": 2, "outUsd": 777.18, "events": 19}, {"token": "0xa361419ad69956d611244520bf3afa88ca783f3e", "symbol": "POND", "ageH": 49.3, "inWhales": 8, "inUsd": 3232.08, "outWhales": 5, "outUsd": 2463.14, "events": 23}, {"token": "0x859ead0ee2fd39a2804bb27713742577f7be79c1", "symbol": "CC", "ageH": 35.6, "inWhales": 4, "inUsd": 4294.45, "outWhales": 2, "outUsd": 1208.69, "events": 9}, {"token": "0x85856f025bf13b8fd2aae2f6da458318744f1e18", "symbol": "CLIPPY", "ageH": 38.3, "inWhales": 5, "inUsd": 3545.61, "outWhales": 3, "outUsd": 1782.95, "events": 13}, {"token": "0xab26d5b48bd07f1248a66fd817036f785078b51d", "symbol": "KANSO", "ageH": 101.9, "inWhales": 8, "inUsd": 4618.45, "outWhales": 2, "outUsd": 589.75, "events": 15}, {"token": "0x6bca58e2ba84ace5a1aba25b793d198450722d28", "symbol": "PMAV", "ageH": 122.6, "inWhales": 3, "inUsd": 2113.7, "outWhales": 2, "outUsd": 2882.31, "events": 13}, {"token": "0x6055706234dd0cc9965400296f2ca950941f6253", "symbol": "AMC", "ageH": 130.3, "inWhales": 6, "inUsd": 1456.5, "outWhales": 1, "outUsd": 3336.06, "events": 47}, {"token": "0xf8bc08092c06db6148114dcf82af881f1085f92b", "symbol": "WOOD", "ageH": 135.6, "inWhales": 3, "inUsd": 887.77, "outWhales": 2, "outUsd": 3839.07, "events": 8}, {"token": "0x0188da44dcc9b6c9d0d80de904c633c5ff227777", "symbol": "GIVEST", "ageH": 116.7, "inWhales": 7, "inUsd": 2052.13, "outWhales": 4, "outUsd": 2568.27, "events": 38}, {"token": "0x01637b14b7378b99de75a64d50656d98488d9a4d", "symbol": "MARIAN", "ageH": 143.4, "inWhales": 8, "inUsd": 4036.12, "outWhales": 1, "outUsd": 3.93, "events": 31}, {"token": "0x493398f141781670506ba543f3c7db9755a67afc", "symbol": "ZA", "ageH": 142.9, "inWhales": 2, "inUsd": 1004.67, "outWhales": 3, "outUsd": 2978.71, "events": 5}, {"token": "0x0d5285841c1aa81d34ca58771676f549dd48ab26", "symbol": "LMEOW", "ageH": 104.3, "inWhales": 5, "inUsd": 3095.15, "outWhales": 3, "outUsd": 773.37, "events": 20}, {"token": "0x0797e99ee536ac34446cdde33e6fab6b1388d075", "symbol": "HOOD", "ageH": 31.5, "inWhales": 3, "inUsd": 1204.71, "outWhales": 2, "outUsd": 2614.91, "events": 16}, {"token": "0xca70d457418b90493e5735de6ec4410c3945498e", "symbol": "WATCH", "ageH": 10.2, "inWhales": 5, "inUsd": 1607.44, "outWhales": 5, "outUsd": 2043.41, "events": 12}, {"token": "0xf05babb8172bea20e974b458c593399be11250dd", "symbol": "GRACE", "ageH": 143.3, "inWhales": 6, "inUsd": 1702.07, "outWhales": 3, "outUsd": 1837.41, "events": 16}, {"token": "0x7aa642e72289be3cafbac8dc529f10fa53bc7777", "symbol": "KOEKI", "ageH": 54.2, "inWhales": 15, "inUsd": 1652.64, "outWhales": 7, "outUsd": 1849.32, "events": 57}, {"token": "0x45634df4e5232af27914a57f2ca3460f81bc35eb", "symbol": "PLM", "ageH": 142.2, "inWhales": 2, "inUsd": 3466.07, "outWhales": 0, "outUsd": 0.0, "events": 2}, {"token": "0xfb1bcb6817f7b8fa86896d3253b16aeb7bd6a5a8", "symbol": "WORTH", "ageH": 143.3, "inWhales": 4, "inUsd": 2.6, "outWhales": 3, "outUsd": 3460.78, "events": 10}, {"token": "0x971804e85821e94d351cee39458da07e0d10faea", "symbol": "Betmore", "ageH": 122.8, "inWhales": 11, "inUsd": 855.82, "outWhales": 13, "outUsd": 2579.16, "events": 27}, {"token": "0xedaee44320107caa714baaec486261a87f27022d", "symbol": "PONGO", "ageH": 143.4, "inWhales": 8, "inUsd": 2279.51, "outWhales": 3, "outUsd": 1074.07, "events": 44}, {"token": "0xe6864e4630d4d7a0cad2e61f6bc2c0dcad777712", "symbol": "LINK", "ageH": 142.2, "inWhales": 7, "inUsd": 2517.3, "outWhales": 3, "outUsd": 658.42, "events": 13}, {"token": "0xdaffa3b70d100286f4fbe1ed6de7c227d94f5912", "symbol": "AGENTIQ", "ageH": 108.8, "inWhales": 1, "inUsd": 1073.62, "outWhales": 1, "outUsd": 2048.84, "events": 3}, {"token": "0x8e62f281f282686fca6dcb39288069a93fc23f1c", "symbol": "HOODRAT", "ageH": 143.2, "inWhales": 6, "inUsd": 3115.21, "outWhales": 0, "outUsd": 0.0, "events": 35}, {"token": "0x8639b074da6a2903faed8da95c0a3cb936f6ad91", "symbol": "CHANGE", "ageH": 50.1, "inWhales": 6, "inUsd": 963.28, "outWhales": 6, "outUsd": 2003.26, "events": 42}, {"token": "0xaa4b6a79df257e50e0079cd812a92262ee3951b0", "symbol": "SUSHICAT", "ageH": 53.9, "inWhales": 5, "inUsd": 2878.44, "outWhales": 0, "outUsd": 0.0, "events": 24}, {"token": "0x4f0ee38e4632901b81c240e9b362701f682ba55e", "symbol": "SHREK", "ageH": 50.8, "inWhales": 9, "inUsd": 1962.19, "outWhales": 3, "outUsd": 877.37, "events": 26}, {"token": "0x364d9f23ede3ada0f5e3f41df10f0a0d01c57777", "symbol": "QUIVER", "ageH": 95.1, "inWhales": 1, "inUsd": 0.0, "outWhales": 3, "outUsd": 2816.05, "events": 4}, {"token": "0x4b1c1725fa83d1a3effe48c992c969788cfac32a", "symbol": "P", "ageH": 48.8, "inWhales": 4, "inUsd": 1535.43, "outWhales": 2, "outUsd": 1240.32, "events": 10}, {"token": "0x48fe62970e2b3962ed9c59f0fce7e5a43b63ea5b", "symbol": "PRIZE", "ageH": 135.6, "inWhales": 3, "inUsd": 0.47, "outWhales": 1, "outUsd": 2758.76, "events": 9}, {"token": "0xc35968c7f5475bb03a43c7382526f4118e01c0de", "symbol": "VISTA", "ageH": 110.0, "inWhales": 3, "inUsd": 1383.95, "outWhales": 2, "outUsd": 1349.07, "events": 10}, {"token": "0x5d86691d883f8962d38fd62136fb761ad3a629ea", "symbol": "MIM", "ageH": 143.4, "inWhales": 7, "inUsd": 1301.79, "outWhales": 2, "outUsd": 1294.69, "events": 23}, {"token": "0x970078468807853bc316432e745165eb34398ba3", "symbol": "URI", "ageH": 128.4, "inWhales": 1, "inUsd": 0.64, "outWhales": 3, "outUsd": 2469.15, "events": 5}, {"token": "0x86a24426d1fc5dfdee454120af3ecc3cc552789b", "symbol": "pow", "ageH": 91.1, "inWhales": 7, "inUsd": 1110.4, "outWhales": 4, "outUsd": 1324.31, "events": 18}, {"token": "0xfe7e19cbce2f896c6c528bc355baf5a768291e18", "symbol": "SPACEHOOD", "ageH": 143.1, "inWhales": 3, "inUsd": 930.71, "outWhales": 2, "outUsd": 1500.22, "events": 5}, {"token": "0x11e6962ec578f394e366bd84ebf46a0643c6a43e", "symbol": "RWA", "ageH": 143.0, "inWhales": 7, "inUsd": 1383.3, "outWhales": 6, "outUsd": 1045.1, "events": 31}, {"token": "0x91e2ce85c223cd55b0cf76ca668a0e61ed696c6b", "symbol": "VLAD", "ageH": 97.1, "inWhales": 8, "inUsd": 1211.39, "outWhales": 5, "outUsd": 1181.08, "events": 30}, {"token": "0x06bc852766ae71b2eaa27f52bbc1d2c1e1dc00cb", "symbol": "RHOODIE", "ageH": 84.4, "inWhales": 2, "inUsd": 1179.56, "outWhales": 1, "outUsd": 1178.98, "events": 5}, {"token": "0x7e86381a763f0ecca2bdf27c54eac403ddd48123", "symbol": "GME", "ageH": 143.3, "inWhales": 6, "inUsd": 2352.73, "outWhales": 0, "outUsd": 0.0, "events": 21}, {"token": "0x8ed8ab093d29e9ccbc26bb38df09910ae1d69125", "symbol": "NUG", "ageH": 50.4, "inWhales": 5, "inUsd": 930.38, "outWhales": 3, "outUsd": 1323.47, "events": 8}, {"token": "0x0af77e27f535256965944e617a386570f5c0432a", "symbol": "STEEL", "ageH": 55.9, "inWhales": 2, "inUsd": 4.5, "outWhales": 1, "outUsd": 2160.01, "events": 9}, {"token": "0xc9e7c34fa156a235e8b8601171a543bc9c84a1b9", "symbol": "TAMPONS", "ageH": 91.7, "inWhales": 8, "inUsd": 754.03, "outWhales": 5, "outUsd": 1302.65, "events": 20}, {"token": "0x7168563b0e70124f0c7c0cf2f13a8d1861baf4a5", "symbol": "BACKED", "ageH": 80.7, "inWhales": 3, "inUsd": 1462.33, "outWhales": 1, "outUsd": 585.05, "events": 8}, {"token": "0x9a763df05b6decb16f7aaa3d565d8f376254d69e", "symbol": "ALPS", "ageH": 97.1, "inWhales": 3, "inUsd": 7.3, "outWhales": 1, "outUsd": 2014.95, "events": 6}, {"token": "0xdbcec8db3e21c1612a22b39d195d7d654cad00af", "symbol": "Jimothy", "ageH": 87.0, "inWhales": 4, "inUsd": 1894.36, "outWhales": 1, "outUsd": 75.23, "events": 14}, {"token": "0x10dc3d3719b507e6bf3fc90c3d327d8590827777", "symbol": "MEMESTOCK", "ageH": 143.2, "inWhales": 3, "inUsd": 12.93, "outWhales": 1, "outUsd": 1944.66, "events": 13}, {"token": "0x327acee9cdd0a8d57ecdfabe8bcecfa88bcf7777", "symbol": "CLUSTER", "ageH": 4.9, "inWhales": 1, "inUsd": 986.76, "outWhales": 1, "outUsd": 967.02, "events": 2}, {"token": "0x5abca8797404e8c870f24f61b3ccd0ed612c98ef", "symbol": "MERAKI", "ageH": 11.1, "inWhales": 4, "inUsd": 275.29, "outWhales": 3, "outUsd": 1657.94, "events": 7}, {"token": "0xe8dfea4ce952be956fad851fc042c7bfb4129271", "symbol": "SHR", "ageH": 141.6, "inWhales": 3, "inUsd": 1738.83, "outWhales": 1, "outUsd": 179.26, "events": 4}, {"token": "0x863ff2b3dd1d7ab2637131b8593926e9e9e170cc", "symbol": "SNOP", "ageH": 135.7, "inWhales": 6, "inUsd": 1087.98, "outWhales": 3, "outUsd": 757.51, "events": 10}, {"token": "0x51db0db68f44baaf6cf0244478918a85497fc944", "symbol": "JUGGERNAUT", "ageH": 143.3, "inWhales": 12, "inUsd": 985.8, "outWhales": 10, "outUsd": 818.2, "events": 42}, {"token": "0xc23d7218512c672ba6e87b7f8bcce53355f55931", "symbol": "BOWLINE", "ageH": 111.2, "inWhales": 4, "inUsd": 23.9, "outWhales": 2, "outUsd": 1757.41, "events": 8}, {"token": "0x432c99bbd9dc1d9040087598d7cf40502d7cc20b", "symbol": "PONSHOOD", "ageH": 51.2, "inWhales": 6, "inUsd": 1012.79, "outWhales": 1, "outUsd": 724.33, "events": 17}, {"token": "0x63519eb1b67b86125837345f6e7251bb8cf47d54", "symbol": "COIN", "ageH": 139.1, "inWhales": 2, "inUsd": 1421.97, "outWhales": 1, "outUsd": 296.42, "events": 6}, {"token": "0x1da047c340b8e7acbb18133d016e7bc2b3d177c9", "symbol": "\u30dd\u30f3\u3055\u3093", "ageH": 139.7, "inWhales": 3, "inUsd": 991.74, "outWhales": 1, "outUsd": 719.02, "events": 9}, {"token": "0x43eea882b845a8493152ebc55cf30ae9281b02d5", "symbol": "FIRE", "ageH": 50.7, "inWhales": 2, "inUsd": 0.17, "outWhales": 1, "outUsd": 1687.7, "events": 3}, {"token": "0xed88fd767eb5527a107ad0b4a36b82cbd50ff9d4", "symbol": "ZTOCKS", "ageH": 18.1, "inWhales": 4, "inUsd": 1004.22, "outWhales": 1, "outUsd": 654.28, "events": 8}, {"token": "0x8fde2c15d44eb7cc1a889bc74633e226f91d3295", "symbol": "ROBINHOODIES", "ageH": 139.1, "inWhales": 3, "inUsd": 331.85, "outWhales": 3, "outUsd": 1268.87, "events": 7}, {"token": "0xc5d1e01536e9893f6fd783394a35e0cf2f96afd6", "symbol": "nice", "ageH": 27.9, "inWhales": 2, "inUsd": 645.89, "outWhales": 2, "outUsd": 941.96, "events": 4}, {"token": "0xf9b3a60ca60b425e8c4f1eca51209770f45374d0", "symbol": "ROBVIS", "ageH": 12.9, "inWhales": 0, "inUsd": 0.0, "outWhales": 1, "outUsd": 1566.55, "events": 1}, {"token": "0xae08f981c507c5eadf65e93c6b671f763a3751e6", "symbol": "KANG", "ageH": 46.2, "inWhales": 6, "inUsd": 840.04, "outWhales": 3, "outUsd": 703.55, "events": 24}, {"token": "0x6689ab375aaaa9aed78aaaba2e8edcc547478cf1", "symbol": "KALEIDO", "ageH": 117.8, "inWhales": 4, "inUsd": 710.32, "outWhales": 1, "outUsd": 820.04, "events": 5}, {"token": "0x73a9999f6e9db138e1ae4595fde049a401161e18", "symbol": "AAPLCAT", "ageH": 83.7, "inWhales": 2, "inUsd": 1068.36, "outWhales": 1, "outUsd": 451.55, "events": 3}, {"token": "0xa80f6f4f07a49f1b34cbd1e7b3ec689d8fb986bd", "symbol": "WOLVES", "ageH": 50.9, "inWhales": 9, "inUsd": 1258.7, "outWhales": 3, "outUsd": 252.07, "events": 14}, {"token": "0x306ea273b78b8ad637fd264638c1025ef32825d7", "symbol": "SZR", "ageH": 140.7, "inWhales": 1, "inUsd": 663.57, "outWhales": 1, "outUsd": 836.18, "events": 2}, {"token": "0x33c8c277d70cb804ad0ea705a5b1559db015252b", "symbol": "STONKS", "ageH": 143.4, "inWhales": 4, "inUsd": 301.89, "outWhales": 4, "outUsd": 1185.35, "events": 9}, {"token": "0x8892a6aa217f7733f3c697faf884877df4d36969", "symbol": "MUNNY", "ageH": 11.3, "inWhales": 0, "inUsd": 0.0, "outWhales": 1, "outUsd": 1430.86, "events": 1}, {"token": "0x06d91369cd89dadad86eeda1763aa136087fbc89", "symbol": "RWA", "ageH": 135.3, "inWhales": 0, "inUsd": 0.0, "outWhales": 1, "outUsd": 1422.85, "events": 1}, {"token": "0xea6de2d7df8595714f295a402299f1669b90fba3", "symbol": "EYESE", "ageH": 83.6, "inWhales": 0, "inUsd": 0.0, "outWhales": 2, "outUsd": 1420.51, "events": 2}, {"token": "0xb13896e409e35c14c29628f0b61804c00c18705e", "symbol": "NOTHING", "ageH": 95.8, "inWhales": 6, "inUsd": 852.49, "outWhales": 2, "outUsd": 559.3, "events": 9}, {"token": "0x4c9d9527c4e3cf9faf70f0df8429d2cced157492", "symbol": "DUMBMONEY", "ageH": 139.0, "inWhales": 3, "inUsd": 1382.13, "outWhales": 0, "outUsd": 0.0, "events": 5}, {"token": "0x28e448946e042c2d4c38f6e80cd724e415ad95bb", "symbol": "CHAD", "ageH": 81.0, "inWhales": 5, "inUsd": 900.37, "outWhales": 1, "outUsd": 470.45, "events": 6}, {"token": "0x232cdfc415d10b673845d83dc02ba2eabe7e30d1", "symbol": "IF", "ageH": 91.7, "inWhales": 5, "inUsd": 1363.95, "outWhales": 0, "outUsd": 0.0, "events": 47}, {"token": "0x17c0ea83edf05859bc9339529ae85fca71301d67", "symbol": "GLS", "ageH": 10.3, "inWhales": 3, "inUsd": 666.91, "outWhales": 1, "outUsd": 666.65, "events": 17}, {"token": "0x0e07565159b1e40caa71d4edf2547cc042014523", "symbol": "WOLVES", "ageH": 54.2, "inWhales": 4, "inUsd": 439.33, "outWhales": 1, "outUsd": 870.35, "events": 14}, {"token": "0x3c6a3a92b8163ecc7b6e3e8e6c2cb00b2c9c7777", "symbol": "530A", "ageH": 142.9, "inWhales": 1, "inUsd": 203.08, "outWhales": 4, "outUsd": 1095.11, "events": 5}, {"token": "0xce8f89b7d4ad8936531d764055e6b1a06e30ab58", "symbol": "ARCHR", "ageH": 102.8, "inWhales": 0, "inUsd": 0.0, "outWhales": 2, "outUsd": 1292.65, "events": 2}, {"token": "0xb6d695d5fbcebd837f6b9f214c9beee8ba90762b", "symbol": "VANTIS", "ageH": 103.8, "inWhales": 0, "inUsd": 0.0, "outWhales": 1, "outUsd": 1287.48, "events": 2}, {"token": "0x45e685b324ef6726099a738d3a5a98f2ccbe29bb", "symbol": "CONVIK", "ageH": 113.5, "inWhales": 2, "inUsd": 0.34, "outWhales": 1, "outUsd": 1285.73, "events": 3}, {"token": "0x4d7b52e644d830d47510440477cb50295d9a8148", "symbol": "4FUN", "ageH": 85.5, "inWhales": 1, "inUsd": 0.08, "outWhales": 1, "outUsd": 1277.66, "events": 2}], "h24": [{"token": "0x0bd7d308f8e1639fab988df18a8011f41eacad73", "symbol": "WETH", "ageH": 143.4, "inWhales": 30, "inUsd": 19716682.7, "outWhales": 7, "outUsd": 635971.28, "events": 86217}, {"token": "0x020bfc650a365f8bb26819deaabf3e21291018b4", "symbol": "CASHCAT", "ageH": 143.4, "inWhales": 73, "inUsd": 1597899.93, "outWhales": 74, "outUsd": 1387181.75, "events": 1489}, {"token": "0x39dbed3a2bd333467115de45665cc57f813c4571", "symbol": "PONS", "ageH": 143.4, "inWhales": 120, "inUsd": 1508087.88, "outWhales": 104, "outUsd": 1454378.87, "events": 2404}, {"token": "0x9727b500ac8726c716f018e5d3ca871481245065", "symbol": "AnsemCat", "ageH": 116.2, "inWhales": 1, "inUsd": 916515.89, "outWhales": 1, "outUsd": 922345.28, "events": 81}, {"token": "0x56910d4409f3a0c78c64dd8d0545ff0705389870", "symbol": "Index", "ageH": 143.3, "inWhales": 75, "inUsd": 642447.67, "outWhales": 58, "outUsd": 764044.12, "events": 879}, {"token": "0x45242320dbb855eea8fd36804c6487e10e97fcf9", "symbol": "TENDIES", "ageH": 142.2, "inWhales": 50, "inUsd": 412654.93, "outWhales": 50, "outUsd": 538575.71, "events": 813}, {"token": "0xe934e36a439c94017b64a3fece66af12099abf50", "symbol": "STONKBROKER", "ageH": 55.8, "inWhales": 38, "inUsd": 381289.39, "outWhales": 38, "outUsd": 328369.75, "events": 801}, {"token": "0xc6911796042b15d7fa4f6cde69e245ddcd3d9c31", "symbol": "VIRTUAL", "ageH": 141.7, "inWhales": 24, "inUsd": 128119.39, "outWhales": 14, "outUsd": 294235.77, "events": 925}, {"token": "0x62c71cd34a52c30d894419cbcc55db2afa8032ea", "symbol": "YOLO", "ageH": 55.9, "inWhales": 44, "inUsd": 225629.26, "outWhales": 38, "outUsd": 179398.76, "events": 607}, {"token": "0x2e8c31162b855a2ffa90f6f8634643ad6f111e18", "symbol": "AI", "ageH": 143.3, "inWhales": 47, "inUsd": 187566.58, "outWhales": 36, "outUsd": 144635.78, "events": 269}, {"token": "0x8ff92566f2e81bdd68edfaa8cde73942a723796b", "symbol": "VEX", "ageH": 143.4, "inWhales": 35, "inUsd": 148540.68, "outWhales": 21, "outUsd": 143130.49, "events": 540}, {"token": "0xd0601ce157db5bdc3162bbac2a2c8af5320d9eec", "symbol": "NVDA", "ageH": 143.2, "inWhales": 10, "inUsd": 70580.95, "outWhales": 60, "outUsd": 153476.68, "events": 170}, {"token": "0xaf4c10fef50059d1e3e8ab1c80e46db6a76098b4", "symbol": "BOWYER", "ageH": 82.9, "inWhales": 39, "inUsd": 107538.8, "outWhales": 40, "outUsd": 116088.04, "events": 503}, {"token": "0xd7321801caae694090694ff55a9323139f043b88", "symbol": "JUGGERNAUT", "ageH": 143.3, "inWhales": 24, "inUsd": 74280.58, "outWhales": 32, "outUsd": 101257.67, "events": 427}, {"token": "0x237c79c93c3eb8c61a2a2a7465a851b0381b8ba3", "symbol": null, "ageH": 18.3, "inWhales": 119, "inUsd": 65571.43, "outWhales": 101, "outUsd": 92180.18, "events": 1863}, {"token": "0x0339f5459fc690ac85f1782e15782a151b4a9e1b", "symbol": "WALLET", "ageH": 143.3, "inWhales": 15, "inUsd": 61953.96, "outWhales": 14, "outUsd": 89337.28, "events": 278}, {"token": "0xf8bc08092c06db6148114dcf82af881f1085f92b", "symbol": "WOOD", "ageH": 135.6, "inWhales": 14, "inUsd": 61805.41, "outWhales": 13, "outUsd": 54589.13, "events": 109}, {"token": "0x8ecea3d0e648db646d824aa51eedeb16ac3d6878", "symbol": "wire", "ageH": 55.3, "inWhales": 28, "inUsd": 69030.74, "outWhales": 24, "outUsd": 46774.24, "events": 475}, {"token": "0x7fe995a80075df3dc8ae11a9b82c7fe4202cd87f", "symbol": "HMM", "ageH": 44.5, "inWhales": 40, "inUsd": 52940.92, "outWhales": 23, "outUsd": 54303.41, "events": 708}, {"token": "0xf0568863195770965a6d8abb0aa87f4314b80320", "symbol": "SLIPPY", "ageH": 109.8, "inWhales": 34, "inUsd": 53559.57, "outWhales": 23, "outUsd": 48653.44, "events": 244}, {"token": "0x3450598e419abb5609f60e4b2fda127ff0897777", "symbol": "FLETCH", "ageH": 142.8, "inWhales": 14, "inUsd": 30887.88, "outWhales": 21, "outUsd": 66201.02, "events": 201}, {"token": "0x791229e3ebd6cfdc3d8157f48722684173c29ad9", "symbol": "SLVR", "ageH": 142.8, "inWhales": 19, "inUsd": 66557.68, "outWhales": 18, "outUsd": 27264.2, "events": 274}, {"token": "0xf2915d1e3c1b0c769d0c756ec43f1c1f6c99cd03", "symbol": "ARROW", "ageH": 142.8, "inWhales": 16, "inUsd": 34505.0, "outWhales": 13, "outUsd": 53666.04, "events": 196}, {"token": "0x77581054581b9c525e7dd7a0155de43867532d03", "symbol": "WISHBONE", "ageH": 143.3, "inWhales": 14, "inUsd": 38827.65, "outWhales": 14, "outUsd": 43582.77, "events": 163}, {"token": "0x45f82ac5d507e988f7406935da8eefe495a360e0", "symbol": "BRODIE", "ageH": 143.4, "inWhales": 39, "inUsd": 39613.44, "outWhales": 31, "outUsd": 39222.11, "events": 214}, {"token": "0x887df15e95423acdd181aed8c6144505e1ea6969", "symbol": null, "ageH": 30.0, "inWhales": 13, "inUsd": 37317.64, "outWhales": 13, "outUsd": 40693.04, "events": 56}, {"token": "0xaa4b6a79df257e50e0079cd812a92262ee3951b0", "symbol": "SUSHICAT", "ageH": 53.9, "inWhales": 7, "inUsd": 27125.72, "outWhales": 13, "outUsd": 42699.14, "events": 114}, {"token": "0x164d9da79722c5294369e79807980e0bff257777", "symbol": "utopia", "ageH": 49.7, "inWhales": 28, "inUsd": 30704.24, "outWhales": 27, "outUsd": 37662.97, "events": 280}, {"token": "0x0188da44dcc9b6c9d0d80de904c633c5ff227777", "symbol": "GIVEST", "ageH": 116.7, "inWhales": 23, "inUsd": 36836.3, "outWhales": 25, "outUsd": 30589.06, "events": 241}, {"token": "0xb47f4702deb124cb4eb6286be83c9d84277c6239", "symbol": "KARMA", "ageH": 95.0, "inWhales": 17, "inUsd": 28796.07, "outWhales": 10, "outUsd": 30844.23, "events": 186}, {"token": "0x1abf16f660ccbaa22ce8646deb1b63635d582228", "symbol": "FONZ", "ageH": 117.4, "inWhales": 22, "inUsd": 21017.74, "outWhales": 19, "outUsd": 35825.11, "events": 363}, {"token": "0x75c8258eaa6d0f94b82951194191ca3efb0bcbe2", "symbol": "MEOW", "ageH": 143.3, "inWhales": 13, "inUsd": 25156.58, "outWhales": 13, "outUsd": 26212.67, "events": 116}, {"token": "0x8f100e99ddf699320724e37cb866770381d47382", "symbol": "ROBINHOOD", "ageH": 143.3, "inWhales": 25, "inUsd": 26372.65, "outWhales": 14, "outUsd": 18894.78, "events": 99}, {"token": "0x4a380618777eed8d513bcd6e983df3c5d2ba7777", "symbol": "RWA", "ageH": 141.9, "inWhales": 18, "inUsd": 21661.1, "outWhales": 14, "outUsd": 22921.23, "events": 172}, {"token": "0x3746a5ebca295dee695dd1bcba50a8626df3099c", "symbol": "HAN", "ageH": 131.0, "inWhales": 10, "inUsd": 15674.8, "outWhales": 11, "outUsd": 22056.19, "events": 53}, {"token": "0x8e62f281f282686fca6dcb39288069a93fc23f1c", "symbol": "HOODRAT", "ageH": 143.2, "inWhales": 12, "inUsd": 16374.9, "outWhales": 9, "outUsd": 20397.51, "events": 183}, {"token": "0x01637b14b7378b99de75a64d50656d98488d9a4d", "symbol": "MARIAN", "ageH": 143.4, "inWhales": 12, "inUsd": 28090.01, "outWhales": 5, "outUsd": 6195.96, "events": 143}, {"token": "0x8ed8ab093d29e9ccbc26bb38df09910ae1d69125", "symbol": "NUG", "ageH": 50.4, "inWhales": 18, "inUsd": 16282.14, "outWhales": 15, "outUsd": 15127.22, "events": 131}, {"token": "0x41af7e794dee45eefab49b6c387eac9368d69c4d", "symbol": "QUANT", "ageH": 56.1, "inWhales": 18, "inUsd": 15348.84, "outWhales": 16, "outUsd": 15785.83, "events": 87}, {"token": "0xf4c450c1570c2dbda91de1ed2e39995a15028c97", "symbol": "HODL", "ageH": 134.3, "inWhales": 14, "inUsd": 18060.14, "outWhales": 5, "outUsd": 12009.15, "events": 103}, {"token": "0xa361419ad69956d611244520bf3afa88ca783f3e", "symbol": "POND", "ageH": 49.3, "inWhales": 19, "inUsd": 12666.29, "outWhales": 17, "outUsd": 16169.06, "events": 169}, {"token": "0x6bca58e2ba84ace5a1aba25b793d198450722d28", "symbol": "PMAV", "ageH": 122.6, "inWhales": 10, "inUsd": 9376.43, "outWhales": 16, "outUsd": 18828.06, "events": 90}, {"token": "0xea6de2d7df8595714f295a402299f1669b90fba3", "symbol": "EYESE", "ageH": 83.6, "inWhales": 11, "inUsd": 13508.28, "outWhales": 11, "outUsd": 13137.76, "events": 27}, {"token": "0x06fcba306b81b049bc3a8431b246f94722c03c38", "symbol": "MOON", "ageH": 130.3, "inWhales": 16, "inUsd": 11833.53, "outWhales": 13, "outUsd": 14716.61, "events": 98}, {"token": "0x48fe62970e2b3962ed9c59f0fce7e5a43b63ea5b", "symbol": "PRIZE", "ageH": 135.6, "inWhales": 6, "inUsd": 2374.07, "outWhales": 8, "outUsd": 22834.14, "events": 63}, {"token": "0x5f94e24a3293cf12c97d8b21c2f960adf471c951", "symbol": "UNICORN", "ageH": 139.0, "inWhales": 11, "inUsd": 11580.58, "outWhales": 6, "outUsd": 12920.42, "events": 87}, {"token": "0x85856f025bf13b8fd2aae2f6da458318744f1e18", "symbol": "CLIPPY", "ageH": 38.3, "inWhales": 15, "inUsd": 10819.19, "outWhales": 13, "outUsd": 11808.08, "events": 64}, {"token": "0x0e07565159b1e40caa71d4edf2547cc042014523", "symbol": "WOLVES", "ageH": 54.2, "inWhales": 10, "inUsd": 17067.8, "outWhales": 5, "outUsd": 5287.61, "events": 105}, {"token": "0x17bb0c898254406b1ea2e8e99b0c263e26c9e4a4", "symbol": "DIH", "ageH": 143.3, "inWhales": 8, "inUsd": 6286.51, "outWhales": 8, "outUsd": 15774.89, "events": 115}, {"token": "0xf44702b17d9abd53815f703e772f35e9c71a53af", "symbol": "RAXOL", "ageH": 137.9, "inWhales": 6, "inUsd": 10780.53, "outWhales": 3, "outUsd": 10181.39, "events": 61}, {"token": "0xbf72347bacefe747eaf48b8a66e38babad3020a0", "symbol": "STONKS", "ageH": 141.8, "inWhales": 12, "inUsd": 15222.66, "outWhales": 5, "outUsd": 5707.42, "events": 110}, {"token": "0x7168563b0e70124f0c7c0cf2f13a8d1861baf4a5", "symbol": "BACKED", "ageH": 80.7, "inWhales": 11, "inUsd": 9987.57, "outWhales": 8, "outUsd": 10541.6, "events": 57}, {"token": "0x53db64dfff64918ffd7c706c9b78a2d627cc0576", "symbol": null, "ageH": 13.4, "inWhales": 15, "inUsd": 9167.49, "outWhales": 23, "outUsd": 11272.4, "events": 130}, {"token": "0x859ead0ee2fd39a2804bb27713742577f7be79c1", "symbol": "CC", "ageH": 35.6, "inWhales": 22, "inUsd": 15389.58, "outWhales": 10, "outUsd": 4700.37, "events": 64}, {"token": "0x600478629dd470fbf2a4145a24899458aab34663", "symbol": "PRINTR", "ageH": 41.2, "inWhales": 11, "inUsd": 9091.98, "outWhales": 9, "outUsd": 10589.46, "events": 49}, {"token": "0xa80eb66b3e0cf66ccb46f8b8c9e7ff5803eeb820", "symbol": "WEN", "ageH": 143.3, "inWhales": 5, "inUsd": 12155.36, "outWhales": 2, "outUsd": 7450.38, "events": 36}, {"token": "0x2443cde7097b4f7ec13596a56f41e8020de9455d", "symbol": null, "ageH": 18.2, "inWhales": 19, "inUsd": 10436.22, "outWhales": 24, "outUsd": 8884.54, "events": 152}, {"token": "0x6f572e8020247324d7b9dc15c297a32e4187df1c", "symbol": null, "ageH": 15.4, "inWhales": 47, "inUsd": 123.37, "outWhales": 34, "outUsd": 18695.88, "events": 307}, {"token": "0x6055706234dd0cc9965400296f2ca950941f6253", "symbol": "AMC", "ageH": 130.3, "inWhales": 14, "inUsd": 9163.41, "outWhales": 10, "outUsd": 9649.13, "events": 146}, {"token": "0x7e86381a763f0ecca2bdf27c54eac403ddd48123", "symbol": "GME", "ageH": 143.3, "inWhales": 12, "inUsd": 7767.26, "outWhales": 8, "outUsd": 10660.04, "events": 82}, {"token": "0xfe7e19cbce2f896c6c528bc355baf5a768291e18", "symbol": "SPACEHOOD", "ageH": 143.1, "inWhales": 10, "inUsd": 8571.47, "outWhales": 7, "outUsd": 9079.81, "events": 38}, {"token": "0xeaa9abb805db03b6859662354abfe0c2a30902ae", "symbol": "SUIT", "ageH": 136.3, "inWhales": 8, "inUsd": 3782.71, "outWhales": 5, "outUsd": 13537.77, "events": 52}, {"token": "0x9e4c1c7025cbe98af0cc0e9936b0c249737ea599", "symbol": "LOLCAT", "ageH": 51.8, "inWhales": 15, "inUsd": 9122.29, "outWhales": 13, "outUsd": 7698.57, "events": 118}, {"token": "0x62c530cd34a50c9d1e296dd8e008ac327cfdc5ff", "symbol": "MM", "ageH": 86.6, "inWhales": 7, "inUsd": 4682.13, "outWhales": 7, "outUsd": 11327.67, "events": 27}, {"token": "0x73a9999f6e9db138e1ae4595fde049a401161e18", "symbol": "AAPLCAT", "ageH": 83.7, "inWhales": 7, "inUsd": 7147.66, "outWhales": 9, "outUsd": 8499.18, "events": 30}, {"token": "0xfb1bcb6817f7b8fa86896d3253b16aeb7bd6a5a8", "symbol": "WORTH", "ageH": 143.3, "inWhales": 6, "inUsd": 1316.53, "outWhales": 6, "outUsd": 14315.79, "events": 34}, {"token": "0x8d4dfaaa4198b6486e0293fec914c2b6a821d4dc", "symbol": "KITSU", "ageH": 143.4, "inWhales": 8, "inUsd": 7645.97, "outWhales": 8, "outUsd": 6883.17, "events": 79}, {"token": "0xd8d1c08a8ba4fc64bac744f74290b89adcb6bf25", "symbol": "SEEDCOIN", "ageH": 143.3, "inWhales": 9, "inUsd": 3839.7, "outWhales": 3, "outUsd": 9956.35, "events": 53}, {"token": "0x43e7cb9984ad95aa808ac21998cc8d5f909e47af", "symbol": "VIM", "ageH": 136.4, "inWhales": 9, "inUsd": 4388.64, "outWhales": 7, "outUsd": 9226.52, "events": 47}, {"token": "0x71d6a215344b61f36514214d9cbace82643f066d", "symbol": "CASHCAT", "ageH": 106.0, "inWhales": 19, "inUsd": 7443.47, "outWhales": 18, "outUsd": 6021.77, "events": 83}, {"token": "0xb9fe2adf7c25ebe4081a2e228b02be05ebdf7410", "symbol": "HOODIO", "ageH": 141.7, "inWhales": 5, "inUsd": 5052.79, "outWhales": 3, "outUsd": 8392.67, "events": 14}, {"token": "0x493398f141781670506ba543f3c7db9755a67afc", "symbol": "ZA", "ageH": 142.9, "inWhales": 5, "inUsd": 2851.28, "outWhales": 5, "outUsd": 10494.85, "events": 16}, {"token": "0x6eda83fc299c10d474068a7e69771c809bcbbba3", "symbol": "AGENTOS", "ageH": 141.2, "inWhales": 9, "inUsd": 5423.52, "outWhales": 8, "outUsd": 7526.17, "events": 43}, {"token": "0x45634df4e5232af27914a57f2ca3460f81bc35eb", "symbol": "PLM", "ageH": 142.2, "inWhales": 9, "inUsd": 9985.82, "outWhales": 4, "outUsd": 2812.86, "events": 20}, {"token": "0x06bc852766ae71b2eaa27f52bbc1d2c1e1dc00cb", "symbol": "RHOODIE", "ageH": 84.4, "inWhales": 17, "inUsd": 7557.4, "outWhales": 11, "outUsd": 4987.15, "events": 60}, {"token": "0x6a4b679a60d3a4057322cfeaaba3dd8f05b5fe8d", "symbol": "401K", "ageH": 42.4, "inWhales": 6, "inUsd": 6174.27, "outWhales": 3, "outUsd": 6108.65, "events": 24}, {"token": "0x14561006002e8f76e68ec69e6a32527730bb73c8", "symbol": "SAGE", "ageH": 49.0, "inWhales": 15, "inUsd": 6445.36, "outWhales": 13, "outUsd": 5832.72, "events": 46}, {"token": "0xb165b9223687db26f26a31d2611d4cf3ebfa3d2e", "symbol": null, "ageH": 13.3, "inWhales": 5, "inUsd": 6069.28, "outWhales": 5, "outUsd": 6069.28, "events": 16}, {"token": "0xa737df5de18e3aa6b0bf8c2e9846ed699f6f2aeb", "symbol": "PONSTAR", "ageH": 143.3, "inWhales": 13, "inUsd": 5967.33, "outWhales": 10, "outUsd": 6144.03, "events": 62}, {"token": "0xc5ac3b7664ba1ac915145cc58f50b89ec3a2970d", "symbol": "KAIRUNE", "ageH": 30.1, "inWhales": 10, "inUsd": 6873.4, "outWhales": 6, "outUsd": 5177.83, "events": 100}, {"token": "0x0af77e27f535256965944e617a386570f5c0432a", "symbol": "STEEL", "ageH": 55.9, "inWhales": 9, "inUsd": 5022.36, "outWhales": 7, "outUsd": 6485.49, "events": 117}, {"token": "0xedaee44320107caa714baaec486261a87f27022d", "symbol": "PONGO", "ageH": 143.4, "inWhales": 8, "inUsd": 7131.21, "outWhales": 3, "outUsd": 4371.04, "events": 70}, {"token": "0x7bf03b84a1bd2fa5e136326426dffa8df6cec618", "symbol": "LOX", "ageH": 142.1, "inWhales": 17, "inUsd": 5385.94, "outWhales": 13, "outUsd": 6022.68, "events": 52}, {"token": "0x40e836f547653691b74c0d68fff60befe36cb024", "symbol": "FAMILY", "ageH": 143.4, "inWhales": 10, "inUsd": 6608.28, "outWhales": 4, "outUsd": 4695.11, "events": 43}, {"token": "0x6689ab375aaaa9aed78aaaba2e8edcc547478cf1", "symbol": "KALEIDO", "ageH": 117.8, "inWhales": 5, "inUsd": 1482.99, "outWhales": 4, "outUsd": 9696.07, "events": 36}, {"token": "0x820d283f7b9b00bc8874ef9e1910bbe8912cb127", "symbol": "BLUEAGENT", "ageH": 116.7, "inWhales": 8, "inUsd": 4075.45, "outWhales": 8, "outUsd": 6645.86, "events": 28}, {"token": "0x0797e99ee536ac34446cdde33e6fab6b1388d075", "symbol": null, "ageH": 31.5, "inWhales": 8, "inUsd": 4521.84, "outWhales": 7, "outUsd": 5019.01, "events": 64}, {"token": "0xf9b3a60ca60b425e8c4f1eca51209770f45374d0", "symbol": null, "ageH": 12.9, "inWhales": 26, "inUsd": 4161.61, "outWhales": 21, "outUsd": 5224.42, "events": 115}, {"token": "0xb85d3321c8ac48382cef0ecd4487a1a91c160ba3", "symbol": "CASB", "ageH": 142.6, "inWhales": 18, "inUsd": 5340.23, "outWhales": 12, "outUsd": 3953.06, "events": 47}, {"token": "0x4c9d9527c4e3cf9faf70f0df8429d2cced157492", "symbol": "DUMBMONEY", "ageH": 139.0, "inWhales": 5, "inUsd": 2721.75, "outWhales": 3, "outUsd": 6346.06, "events": 31}, {"token": "0xca70d457418b90493e5735de6ec4410c3945498e", "symbol": null, "ageH": 10.2, "inWhales": 8, "inUsd": 2311.63, "outWhales": 13, "outUsd": 6732.75, "events": 110}, {"token": "0x186c9122868401c05d56fa5984867417ece07777", "symbol": "Stockcoin", "ageH": 55.5, "inWhales": 11, "inUsd": 3859.44, "outWhales": 7, "outUsd": 5181.73, "events": 44}, {"token": "0x57c0e45cb534413d1c20a4240955d6bb250bb4f1", "symbol": "UP", "ageH": 133.9, "inWhales": 4, "inUsd": 68.04, "outWhales": 2, "outUsd": 8971.52, "events": 20}, {"token": "0x364d9f23ede3ada0f5e3f41df10f0a0d01c57777", "symbol": "QUIVER", "ageH": 95.1, "inWhales": 7, "inUsd": 4252.19, "outWhales": 8, "outUsd": 4718.71, "events": 36}, {"token": "0xc35968c7f5475bb03a43c7382526f4118e01c0de", "symbol": "VISTA", "ageH": 110.0, "inWhales": 6, "inUsd": 5312.86, "outWhales": 3, "outUsd": 3487.6, "events": 74}, {"token": "0xe59e2953334cc1664181976d79c4b5d39eab7777", "symbol": "PACKS", "ageH": 56.0, "inWhales": 7, "inUsd": 5642.23, "outWhales": 5, "outUsd": 3130.03, "events": 34}, {"token": "0x31ef2f4e678b3640a380c5882ae1a73763d138e9", "symbol": "FLOWR", "ageH": 135.6, "inWhales": 5, "inUsd": 4283.64, "outWhales": 2, "outUsd": 4109.3, "events": 28}, {"token": "0x385354ac9cc1bfc1776df4e65a33ee2278631d8d", "symbol": "GAPPY", "ageH": 117.0, "inWhales": 9, "inUsd": 4653.21, "outWhales": 4, "outUsd": 3704.98, "events": 31}, {"token": "0xf444f3c77c77a33f7c8d8fcab8a1e88afb843da5", "symbol": "SQUEEZE", "ageH": 134.6, "inWhales": 6, "inUsd": 3845.96, "outWhales": 4, "outUsd": 4180.67, "events": 133}, {"token": "0xd125f8f710b052b66ae5ef2113957c83d25a7777", "symbol": "HOODED", "ageH": 29.3, "inWhales": 16, "inUsd": 4936.5, "outWhales": 9, "outUsd": 3037.59, "events": 84}, {"token": "0x26879c326b7664f9fee7fa83e9274eea800ead7c", "symbol": "CORTEX", "ageH": 99.1, "inWhales": 6, "inUsd": 2401.0, "outWhales": 8, "outUsd": 5333.25, "events": 25}, {"token": "0x27c5a4353a710af81a27c5386f0dc93a26efeea8", "symbol": "MARS", "ageH": 50.6, "inWhales": 8, "inUsd": 5447.62, "outWhales": 5, "outUsd": 2286.12, "events": 16}, {"token": "0x0d5285841c1aa81d34ca58771676f549dd48ab26", "symbol": "LMEOW", "ageH": 104.3, "inWhales": 8, "inUsd": 4544.32, "outWhales": 7, "outUsd": 3112.5, "events": 33}, {"token": "0x2711aa54ab08f448826a0d93ed4c043189827777", "symbol": "APPLCAT", "ageH": 56.1, "inWhales": 9, "inUsd": 3479.21, "outWhales": 8, "outUsd": 4176.48, "events": 52}, {"token": "0x24ecd17cb8d054304c1080299e3f4050ff2801a7", "symbol": "FRANKLIN", "ageH": 49.4, "inWhales": 14, "inUsd": 4640.1, "outWhales": 6, "outUsd": 2861.87, "events": 51}, {"token": "0x407470f85e0b342a52aae2f191e135cef2947777", "symbol": "MIZUKARA", "ageH": 116.2, "inWhales": 7, "inUsd": 5542.91, "outWhales": 2, "outUsd": 1949.59, "events": 116}, {"token": "0x379ea14ec774d53880f2f843281a7c8e9c48c26a", "symbol": "CLINE", "ageH": 52.3, "inWhales": 10, "inUsd": 4049.44, "outWhales": 5, "outUsd": 3394.95, "events": 105}, {"token": "0x970078468807853bc316432e745165eb34398ba3", "symbol": "URI", "ageH": 128.4, "inWhales": 11, "inUsd": 3211.52, "outWhales": 6, "outUsd": 4183.21, "events": 32}, {"token": "0x8639b074da6a2903faed8da95c0a3cb936f6ad91", "symbol": "CHANGE", "ageH": 50.1, "inWhales": 15, "inUsd": 3869.24, "outWhales": 12, "outUsd": 3458.41, "events": 93}, {"token": "0xbe4f4bc2ecdca72a6e0d9c963ad71a5869a9fa65", "symbol": "TRASH", "ageH": 143.3, "inWhales": 6, "inUsd": 3526.3, "outWhales": 8, "outUsd": 3743.78, "events": 25}, {"token": "0x9a763df05b6decb16f7aaa3d565d8f376254d69e", "symbol": "ALPS", "ageH": 97.1, "inWhales": 10, "inUsd": 4204.17, "outWhales": 3, "outUsd": 2864.9, "events": 24}, {"token": "0x7541872e32bb529d7ff11d6c59832269ce33a6ff", "symbol": "MONVERA", "ageH": 139.6, "inWhales": 7, "inUsd": 3194.36, "outWhales": 5, "outUsd": 3750.38, "events": 18}, {"token": "0xdbcec8db3e21c1612a22b39d195d7d654cad00af", "symbol": "Jimothy", "ageH": 87.0, "inWhales": 13, "inUsd": 4731.45, "outWhales": 7, "outUsd": 2174.14, "events": 89}, {"token": "0xd374595b39069a56ee5da6592f9252d366e53482", "symbol": "MISSION", "ageH": 56.1, "inWhales": 0, "inUsd": 0.0, "outWhales": 3, "outUsd": 6699.6, "events": 3}, {"token": "0x0417045cc5046961aeb4b574f7d88daec04bb239", "symbol": "Aros", "ageH": 134.3, "inWhales": 4, "inUsd": 5432.34, "outWhales": 2, "outUsd": 1178.62, "events": 12}, {"token": "0x6e6492e4cada1c69ce4735ef0a393a51a43ca008", "symbol": "ROAR", "ageH": 42.5, "inWhales": 73, "inUsd": 3585.52, "outWhales": 64, "outUsd": 2908.41, "events": 766}, {"token": "0x232cdfc415d10b673845d83dc02ba2eabe7e30d1", "symbol": "IF", "ageH": 91.7, "inWhales": 7, "inUsd": 3586.24, "outWhales": 3, "outUsd": 2786.02, "events": 162}, {"token": "0x28e448946e042c2d4c38f6e80cd724e415ad95bb", "symbol": "CHAD", "ageH": 81.0, "inWhales": 19, "inUsd": 3766.05, "outWhales": 9, "outUsd": 2569.65, "events": 47}, {"token": "0x9e94c8b5a0caeda5d0471c3a9f5ed4f3519d88c7", "symbol": "ROCKET", "ageH": 8.1, "inWhales": 15, "inUsd": 5292.52, "outWhales": 5, "outUsd": 947.52, "events": 44}, {"token": "0x79fe86b963255ce884bdcac6388c50a599ba277f", "symbol": "ROBINHOOD", "ageH": 142.6, "inWhales": 4, "inUsd": 226.37, "outWhales": 5, "outUsd": 5902.92, "events": 54}]}}